scrapy_spiders/__init__.py
scrapy_spiders/xls.py
scrapy_spiders-0.0.2.dist-info/METADATA
scrapy_spiders-0.0.2.dist-info/RECORD
scrapy_spiders-0.0.2.dist-info/WHEEL
scrapy_spiders-0.0.2.dist-info/top_level.txt
spiders/__init__.py
spiders/xls.py
