Metadata-Version: 2.1
Name: scrapy-spiders
Version: 0.0.2
Summary: Spiders for scrapy
Home-page: https://github.com/quick-sort/scrapy-spiders.git
Author: quicksort
Author-email: quicksort@outlook.com
License: UNKNOWN
Platform: UNKNOWN
Classifier: Programming Language :: Python :: 3
Classifier: License :: OSI Approved :: MIT License
Classifier: Operating System :: OS Independent
Requires-Python: >=3.5
Requires-Dist: xlrd
Requires-Dist: scrapy
